{
  "games": [
    {
      "name": "Holiday Towers",
      "is_active": true,
      "bets": [
        {
          "theoretical_payoff_rate": 0.93,
          "cost": [
            0.5,
            1,
            2.5,
            5,
            10,
            15,
            20,
            25,
            50
          ]
        }
      ]
    },
    {
      "name": "Home for the Holly-Days",
      "is_active": true,
      "bets": [
        {
          "theoretical_payoff_rate": 0.8705,
          "cost": [
            0.5,
            1,
            2,
            5,
            10
          ]
        }
      ]
    },
    {
      "name": "Lotto 6/49 Express",
      "is_active": true,
      "bets": [
        {
          "theoretical_payoff_rate": 0.85,
          "cost": [
            1
          ]
        }
      ]
    },
    {
      "name": "Merry Multiplier",
      "is_active": true,
      "bets": [
        {
          "theoretical_payoff_rate": 0.8479,
          "cost": [
            3
          ]
        },
        {
          "theoretical_payoff_rate": 0.85,
          "cost": [
            1,
            2,
            4,
            5
          ]
        }
      ]
    },
    {
      "name": "Mots cachés 50 years",
      "is_active": true,
      "bets": [
        {
          "theoretical_payoff_rate": 0.64,
          "cost": [
            2
          ]
        }
      ]
    }
  ]
}
